LICENSE
MANIFEST.in
README.rst
setup.py
cbsettings/__init__.py
cbsettings/decorators.py
cbsettings/exceptions.py
cbsettings/importers.py
cbsettings/pkgmeta.py
cbsettings/settings.py
cbsettings/switching/__init__.py
cbsettings/switching/checks.py
django_classbasedsettings.egg-info/PKG-INFO
django_classbasedsettings.egg-info/SOURCES.txt
django_classbasedsettings.egg-info/dependency_links.txt
django_classbasedsettings.egg-info/not-zip-safe
django_classbasedsettings.egg-info/requires.txt
django_classbasedsettings.egg-info/top_level.txt
tests/__init__.py
tests/basic_tests.py
tests/callable_settings_tests.py
tests/prefixed_settings_tests.py
tests/settings.py
tests/switcher_tests.py
tests/utils.py