Metadata-Version: 1.1
Name: django-classbasedsettings
Version: 1.5.0
Summary: Use classes to define settings.
Home-page: http://github.com/matthewwithanm/django-classbasedsettings
Author: Matthew Tretter
Author-email: m@tthewwithanm.com
License: UNKNOWN
Download-URL: http://github.com/matthewwithanm/django-classbasedsettings/tarball/master
Keywords: settings,classbased,class-based
Platform: UNKNOWN
Classifier: Environment :: Web Environment
Classifier: Framework :: Django
Classifier: Intended Audience :: Developers
Classifier: License :: OSI Approved :: BSD License
Classifier: Operating System :: OS Independent
Classifier: Programming Language :: Python :: 2.7
Classifier: Programming Language :: Python :: 3.4
Classifier: Topic :: Utilities
